jrnr/__init__.py
jrnr/_compat.py
jrnr/cli.py
jrnr/jrnr.py
jrnr-0.2.4.dist-info/AUTHORS.rst
jrnr-0.2.4.dist-info/LICENSE
jrnr-0.2.4.dist-info/METADATA
jrnr-0.2.4.dist-info/WHEEL
jrnr-0.2.4.dist-info/entry_points.txt
jrnr-0.2.4.dist-info/top_level.txt
jrnr-0.2.4.dist-info/RECORD
