Metadata-Version: 2.1
Name: jrnr
Version: 0.2.4
Summary: Job Runner for Climate Impact Lab Jobs
Home-page: https://upload.pypi.org/legacy/
Author: Michael Delgado
Author-email: mdelgado@rhg.com
License: MIT license
Keywords: jrnr
Platform: UNKNOWN
Classifier: Development Status :: 2 - Pre-Alpha
Classifier: Intended Audience :: Developers
Classifier: License :: OSI Approved :: MIT License
Classifier: Natural Language :: English
Classifier: Programming Language :: Python :: 3
Classifier: Programming Language :: Python :: 3.5
Classifier: Programming Language :: Python :: 3.6
Classifier: Programming Language :: Python :: 3.7
Requires-Dist: Click (>=6.0)
